tgstattools/__init__.py
tgstattools/__main__.py
tgstattools/cli.py
tgstattools/commands/__init__.py
tgstattools/commands/config_commands.py
tgstattools/commands/data_commands.py
tgstattools/commands/database_commands.py
tgstattools/commands/demo_enhanced_stats.py
tgstattools/commands/maintenance_commands.py
tgstattools/commands/manual_commands.py
tgstattools/commands/session_commands.py
tgstattools/commands/simple_commands.py
tgstattools/commands/stats_commands.py
tgstattools/commands/session/__init__.py
tgstattools/commands/session/cli_handlers.py
tgstattools/commands/session/connection_tester.py
tgstattools/commands/session/input_collector.py
tgstattools/commands/session/output_formatter.py
tgstattools/commands/session/session_auth_service.py
tgstattools/commands/session/session_validator.py
tgstattools/core/__init__.py
tgstattools/core/config_manager.py
tgstattools/core/telegram_client.py
tgstattools/core/timezone_utils.py
tgstattools/core/utils.py
tgstattools/core/config/__init__.py
tgstattools/core/config/config_factory.py
tgstattools/core/config/config_loader.py
tgstattools/core/config/config_validator.py
tgstattools/core/config/environment_manager.py
tgstattools/core/config/group_manager.py
tgstattools/core/data_viewer/__init__.py
tgstattools/core/data_viewer/data_processor.py
tgstattools/core/data_viewer/data_query_engine.py
tgstattools/core/data_viewer/period_manager.py
tgstattools/core/database/__init__.py
tgstattools/core/database/cache_service.py
tgstattools/core/database/connection.py
tgstattools/core/database/schema_manager.py
tgstattools/core/database/schema_manager_old.py
tgstattools/core/database/statistics_repository.py
tgstattools/core/database/schema/__init__.py
tgstattools/core/database/schema/db_statistics.py
tgstattools/core/database/schema/index_manager.py
tgstattools/core/database/schema/migration_runner.py
tgstattools/core/database/schema/schema_creator.py
tgstattools/core/database/schema/schema_validator.py
tgstattools-2.2.0.dist-info/licenses/LICENSE
tgstattools-2.2.0.dist-info/METADATA
tgstattools-2.2.0.dist-info/WHEEL
tgstattools-2.2.0.dist-info/entry_points.txt
tgstattools-2.2.0.dist-info/top_level.txt
tgstattools-2.2.0.dist-info/RECORD
