Metadata-Version: 2.4
Name: tgstattools
Version: 2.2.0
Summary: Advanced Telegram chat statistics collection and reporting daemon
Author-email: TgStatTools Team <team@tgstattools.dev>
License-Expression: Unlicense
Classifier: Development Status :: 4 - Beta
Classifier: Intended Audience :: Developers
Classifier: Programming Language :: Python :: 3
Classifier: Programming Language :: Python :: 3.9
Classifier: Programming Language :: Python :: 3.10
Classifier: Programming Language :: Python :: 3.11
Classifier: Programming Language :: Python :: 3.12
Classifier: Topic :: Communications :: Chat
Classifier: Topic :: System :: Monitoring
Requires-Python: >=3.9
License-File: LICENSE
Requires-Dist: telethon>=1.24.0
Requires-Dist: python-dotenv>=1.0.0
Requires-Dist: python-dateutil>=2.8.2
Requires-Dist: colorama>=0.4.6
Requires-Dist: aiofiles>=23.2.0
Requires-Dist: pytz>=2023.3
Provides-Extra: dev
Requires-Dist: pytest>=7.0.0; extra == "dev"
Requires-Dist: pytest-cov>=4.0.0; extra == "dev"
Requires-Dist: black>=23.0.0; extra == "dev"
Requires-Dist: isort>=5.12.0; extra == "dev"
Requires-Dist: flake8>=6.0.0; extra == "dev"
Requires-Dist: mypy>=1.0.0; extra == "dev"
Dynamic: license-file
